{"assets":{"D266685DD18997A93464E74822C407CB":{"type":"texture","index":35,"assetRequest":{"type":"slide","state":"incoming","slide":"0B85B5D7-4EF5-43B9-9FD7-FFB34EB4F1FC"},"url":{"web":"assets/D266685DD18997A93464E74822C407CB.png"},"width":1920,"height":1080},"2C58A56E937CCB2D635B90B6883631B4":{"type":"texture","index":34,"assetRequest":{"type":"slide","state":"outgoing","slide":"23AEF8D0-7F50-45BF-A890-B1B9817AEF37"},"url":{"web":"assets/2C58A56E937CCB2D635B90B6883631B4.png"},"width":1920,"height":1080}},"events":[{"effects":[{"beginTime":0,"baseLayer":{"animations":[],"initialState":{"affineTransform":[1,0,0,1,0,0],"masksToBounds":false,"rotation":0,"scale":1,"position":{"pointX":960,"pointY":540},"width":1920,"sublayerTransform":[1,0,0,0,0,1,0,0,0,0,1,0,0,0,0,1],"contentsRect":{"y":0,"x":0,"width":1,"height":1},"opacity":1,"edgeAntialiasingMask":251658240,"height":1080,"hidden":false,"anchorPoint":{"pointX":0.5,"pointY":0.5}},"objectID":"0","layers":[{"animations":[],"initialState":{"affineTransform":[1,0,0,1,0,0],"masksToBounds":false,"rotation":0,"scale":1,"position":{"pointX":960,"pointY":540},"width":1920,"sublayerTransform":[1,0,0,0,0,1,0,0,0,0,1,-0.0003500791246677598,0,0,0,1],"contentsRect":{"y":0,"x":0,"width":1,"height":1},"opacity":1,"edgeAntialiasingMask":251658240,"height":1080,"hidden":false,"anchorPoint":{"pointX":0.5,"pointY":0.5}},"layers":[{"animations":[],"layers":[],"initialState":{"affineTransform":[1,0,0,1,0,0],"masksToBounds":false,"rotation":0,"scale":1,"position":{"pointX":960,"pointY":540},"width":1920,"sublayerTransform":[1,0,0,0,0,1,0,0,0,0,1,0,0,0,0,1],"contentsRect":{"y":0,"x":0,"width":1,"height":1},"opacity":1,"edgeAntialiasingMask":0,"height":1080,"hidden":false,"anchorPoint":{"pointX":0.5,"pointY":0.5}},"texture":"D266685DD18997A93464E74822C407CB"},{"animations":[{"timeOffset":0,"from":{"scalar":false},"beginTime":0,"repeatCount":0,"fillMode":"both","property":"hidden","autoreverses":false,"duration":0.01,"to":{"scalar":true}}],"layers":[],"initialState":{"affineTransform":[1,0,0,1,0,0],"masksToBounds":false,"rotation":0,"scale":1,"position":{"pointX":960,"pointY":540},"width":1920,"sublayerTransform":[1,0,0,0,0,1,0,0,0,0,1,0,0,0,0,1],"contentsRect":{"y":0,"x":0,"width":1,"height":1},"opacity":1,"edgeAntialiasingMask":0,"height":1080,"hidden":false,"anchorPoint":{"pointX":0.5,"pointY":0.5}},"texture":"2C58A56E937CCB2D635B90B6883631B4"}]}]},"effects":[],"duration":0.01,"type":"transition","name":"none","objectID":"0"}],"automaticPlay":false,"hyperlinks":[],"accessibility":[{"text":"Broker 实现数据存储的服务器，Kafka集群包含一个或多个服务器","targetRectangle":{"y":310,"x":187.7199990853896,"width":1331.10536,"height":65}},{"text":"Topic 用来对消息进行分类，每个进入到Kafka的信息都会被放到一个Topic下","targetRectangle":{"y":375,"x":187.1578957140446,"width":1495.8675,"height":114.5656241551042}},{"text":"Partition 每个Topic中的消息会被分为若干个Partition，以提高消息的处理效率","targetRectangle":{"y":489.5656241551042,"x":187.7199990853896,"width":1570.18784,"height":117.5099991559982}},{"text":"Producer 消息的生产者，负责发布消息到Kafka broker","targetRectangle":{"y":607.0756233111024,"x":187.7199990853896,"width":1114.32984,"height":117.5099991559982}},{"text":"Consumer 消息的消费者，向Kafka broker读取消息的客户端","targetRectangle":{"y":724.5856224671006,"x":187.7199990853896,"width":1230.86288,"height":117.5099991559982}},{"text":"Consumer Group 消息的消费群组","targetRectangle":{"y":842.0956216230989,"x":187.7199990853896,"width":693.4595200000001,"height":117.5099991559982}},{"text":"Kafka相关术语","targetRectangle":{"y":84,"x":593.308,"width":734.384,"height":157}}],"baseLayer":{"animations":[],"initialState":{"affineTransform":[1,0,0,1,0,0],"masksToBounds":false,"rotation":0,"scale":1,"position":{"pointX":960,"pointY":540},"width":1920,"sublayerTransform":[1,0,0,0,0,1,0,0,0,0,1,0,0,0,0,1],"contentsRect":{"y":0,"x":0,"width":1,"height":1},"opacity":1,"edgeAntialiasingMask":251658240,"height":1080,"hidden":false,"anchorPoint":{"pointX":0.5,"pointY":0.5}},"objectID":"0","layers":[{"animations":[],"initialState":{"affineTransform":[1,0,0,1,0,0],"masksToBounds":false,"rotation":0,"scale":1,"position":{"pointX":960,"pointY":540},"width":1920,"sublayerTransform":[1,0,0,0,0,1,0,0,0,0,1,-0.0003500791246677598,0,0,0,1],"contentsRect":{"y":0,"x":0,"width":1,"height":1},"opacity":1,"edgeAntialiasingMask":251658240,"height":1080,"hidden":false,"anchorPoint":{"pointX":0.5,"pointY":0.5}},"layers":[{"animations":[],"layers":[],"initialState":{"affineTransform":[1,0,0,1,0,0],"masksToBounds":false,"rotation":0,"scale":1,"position":{"pointX":960,"pointY":540},"width":1920,"sublayerTransform":[1,0,0,0,0,1,0,0,0,0,1,0,0,0,0,1],"contentsRect":{"y":0,"x":0,"width":1,"height":1},"opacity":1,"edgeAntialiasingMask":0,"height":1080,"hidden":false,"anchorPoint":{"pointX":0.5,"pointY":0.5}},"texture":"2C58A56E937CCB2D635B90B6883631B4"}]}]}}]}